{
  "main": {
    "id": "d986a82d26590f59",
    "type": "split",
    "children": [
      {
        "id": "61776d6b334ccd35",
        "type": "tabs",
        "children": [
          {
            "id": "f7cb7d0c67cbaacf",
            "type": "leaf",
            "state": {
              "type": "graph",
              "state": {}
            }
          }
        ]
      }
    ],
    "direction": "vertical"
  },
  "left": {
    "id": "cbc41e26defe1579",
    "type": "split",
    "children": [
      {
        "id": "231ce0156d13e923",
        "type": "tabs",
        "children": [
          {
            "id": "b798dbadde317bea",
            "type": "leaf",
            "state": {
              "type": "file-explorer",
              "state": {
                "sortOrder": "alphabetical"
              }
            }
          },
          {
            "id": "2f1b57ad041c73d2",
            "type": "leaf",
            "state": {
              "type": "search",
              "state": {
                "query": "",
                "matchingCase": false,
                "explainSearch": false,
                "collapseAll": false,
                "extraContext": false,
                "sortOrder": "alphabetical"
              }
            }
          },
          {
            "id": "226bd3a8baed63f1",
            "type": "leaf",
            "state": {
              "type": "bookmarks",
              "state": {}
            }
          }
        ]
      }
    ],
    "direction": "horizontal",
    "width": 300
  },
  "right": {
    "id": "0d638cb66896e90b",
    "type": "split",
    "children": [
      {
        "id": "11923e7594739548",
        "type": "tabs",
        "children": [
          {
            "id": "b3516d9b95023eec",
            "type": "leaf",
            "state": {
              "type": "backlink",
              "state": {
                "collapseAll": false,
                "extraContext": false,
                "sortOrder": "alphabetical",
                "showSearch": false,
                "searchQuery": "",
                "backlinkCollapsed": false,
                "unlinkedCollapsed": true
              }
            }
          },
          {
            "id": "88a9a84fa89ac957",
            "type": "leaf",
            "state": {
              "type": "outgoing-link",
              "state": {
                "linksCollapsed": false,
                "unlinkedCollapsed": true
              }
            }
          },
          {
            "id": "4f1d17719fca5f42",
            "type": "leaf",
            "state": {
              "type": "tag",
              "state": {
                "sortOrder": "frequency",
                "useHierarchy": true
              }
            }
          },
          {
            "id": "42b038ade62a285f",
            "type": "leaf",
            "state": {
              "type": "outline",
              "state": {}
            }
          }
        ]
      }
    ],
    "direction": "horizontal",
    "width": 300,
    "collapsed": true
  },
  "left-ribbon": {
    "hiddenItems": {
      "switcher:Open quick switcher": false,
      "graph:Open graph view": false,
      "canvas:Create new canvas": false,
      "daily-notes:Open today's daily note": false,
      "templates:Insert template": false,
      "command-palette:Open command palette": false
    }
  },
  "active": "f7cb7d0c67cbaacf",
  "lastOpenFiles": [
    "Desarrollo de software/Git & GitHub/Configuracion.md",
    "ingles.md",
    "Expectativas con el programa ONE.md",
    "arqui.md",
    "Universidad/0 - Universidad.md",
    "Universidad/Proyecto de ingenieria I/Roles en proyectos de software.md",
    "Universidad/Proyecto de ingenieria I/Prototipos.md",
    "Universidad/Proyecto de ingenieria I/Metricas de Software.md",
    "Universidad/Proyecto de ingenieria I/Fases del desarrollo de Software.md",
    "Universidad/Proyecto de ingenieria I/Diseño de Software.md",
    "Universidad/Proyecto de ingenieria I/Descomposición modular.md",
    "Universidad/Proyecto de ingenieria I/0 - Proyecto de ingenieria I.md",
    "Universidad/Proyecto de ingenieria I",
    "Universidad/Images/Proyecto de ingenieria I/Wireframes.png",
    "Universidad/Images/Proyecto de ingenieria I/valor_factor_ajuste.png",
    "Universidad/Images/Proyecto de ingenieria I/tester_software.png",
    "Universidad/Images/Proyecto de ingenieria I/rendimiento.png",
    "Universidad/Images/Proyecto de ingenieria I/refinamiento.png",
    "Universidad/Images/Proyecto de ingenieria I/pruebas.png",
    "Universidad/Images/Proyecto de ingenieria I/prototipo_bajo_nivel.png",
    "Universidad/Images/Proyecto de ingenieria I/prototipo_2.png",
    "Universidad/Images/Proyecto de ingenieria I/prototipo_1.png",
    "Universidad/Images/Proyecto de ingenieria I/proceso_prototipo.png",
    "Universidad/Images/Proyecto de ingenieria I",
    "Universidad/Images/Estructuras de datos no lineales",
    "Universidad/Images/Estructuras de datos lineales",
    "Universidad/Images",
    "Universidad/Estructuras de datos no lineales/Introduccion.md",
    "Universidad/Estructuras de datos no lineales/Arboles.md",
    "Universidad/Estructuras de datos no lineales/Arboles binarios.md",
    "Universidad/Estructuras de datos no lineales/Arboles binarios de busqueda.md",
    "Universidad/Estructuras de datos no lineales/Árboles B.md",
    "Universidad/Estructuras de datos no lineales/0 - Estructuras de datos no lineales.md",
    "Universidad/Estructuras de datos no lineales",
    "Universidad/Estructuras de datos lineales/Pilas.md",
    "Universidad/Estructuras de datos lineales/Listas enlazadas.md",
    "Universidad/Estructuras de datos lineales/Alojamiento de memoria en C.md",
    "Universidad/Estructuras de datos lineales/Administracion de memoria.md",
    "Universidad/Estructuras de datos lineales/0 - Estructuras de datos lineales.md",
    "Universidad/Estructuras de datos lineales",
    "Universidad/Arquitectura de computadoras/Sistemas combinacionales y secuenciales.md",
    "Universidad/Arquitectura de computadoras/Organización y arquitectura.md",
    "Universidad/Arquitectura de computadoras/Lenguaje de bajo nivel.md",
    "Universidad/Arquitectura de computadoras",
    "Universidad",
    "Gallery"
  ]
}